pybooster/__init__.py
pybooster/py.typed
pybooster/types.py
pybooster/_private/__init__.py
pybooster/_private/_injector.py
pybooster/_private/_provider.py
pybooster/_private/_solution.py
pybooster/_private/_utils.py
pybooster/core/__init__.py
pybooster/core/injector.py
pybooster/core/provider.py
pybooster/core/scope.py
pybooster/core/solution.py
pybooster/core/state.py
pybooster/extra/__init__.py
pybooster/extra/_utils.py
pybooster/extra/asgi.py
pybooster/extra/sqlalchemy.py
pybooster-0.0.10.dist-info/METADATA
pybooster-0.0.10.dist-info/WHEEL
pybooster-0.0.10.dist-info/licenses/LICENSE.txt
pybooster-0.0.10.dist-info/RECORD
