Metadata-Version: 2.4
Name: pybooster
Version: 0.0.10
Summary: Dependency injection without the boilerplate.
Project-URL: Source, https://github.com/rmorshea/pybooster
Project-URL: Documentation, https://ryanmorshead.com/pybooster
Author-email: Ryan Morshead <ryan.morshead@gmail.com>
License: MIT License
License-File: LICENSE.txt
Keywords: dependency,framework,injection
Classifier: Development Status :: 4 - Beta
Classifier: Programming Language :: Python
Classifier: Programming Language :: Python :: Implementation :: CPython
Classifier: Programming Language :: Python :: Implementation :: PyPy
Requires-Python: <4,>=3.11
Requires-Dist: paramorator<2,>=1.0.2
Requires-Dist: rustworkx<0.16,>=0.15
Requires-Dist: typing-extensions
Provides-Extra: sqlalchemy
Requires-Dist: sqlalchemy[asyncio]<3,>=2; extra == 'sqlalchemy'
